sloth/__init__.py
sloth/__main__.py
sloth/_types.py
sloth/_utils.py
sloth/simple.py
sloth/timers.py
sloth/raw/__init__.py
sloth/raw/base.py
sloth/raw/runners.py
sloth/raw/tests.py
sloth_speedtest-0.2.post1.dist-info/LICENSE
sloth_speedtest-0.2.post1.dist-info/METADATA
sloth_speedtest-0.2.post1.dist-info/WHEEL
sloth_speedtest-0.2.post1.dist-info/entry_points.txt
sloth_speedtest-0.2.post1.dist-info/top_level.txt
sloth_speedtest-0.2.post1.dist-info/RECORD
