Metadata-Version: 2.1
Name: sloth-speedtest
Version: 0.2.post1
Summary: The best python speedtesting library and command line tool
Home-page: https://github.com/fluffykoalas/sloth
Author: Legorooj
Author-email: legorooj@protonmail.com
Maintainer: Legorooj, FluffyKoalas
License: MIT
Project-URL: Bug Tracker, https://github.com/fluffykoalas/sloth/issues
Project-URL: Documentation, https://sloth.fluffykoalas.org/en/stable
Project-URL: Source Code, https://github.com/fluffykoalas/sloth
Keywords: python speed speedtesting testing speedtest awesome cli sloth
Platform: UNKNOWN
Classifier: Intended Audience :: Developers
Classifier: Development Status :: 3 - Alpha
Classifier: License :: OSI Approved :: MIT License
Classifier: Natural Language :: English
Classifier: Operating System :: OS Independent
Classifier: Programming Language :: Python
Classifier: Programming Language :: Python :: 3 :: Only
Classifier: Programming Language :: Python :: 3.5
Classifier: Programming Language :: Python :: 3.6
Classifier: Programming Language :: Python :: 3.7
Classifier: Programming Language :: Python :: 3.8
Classifier: Topic :: Software Development :: Testing
Requires-Python: >=3.5
Requires-Dist: click
